Metadata-Version: 2.4
Name: xkings
Version: 0.1.2
Summary: Ein einfacher Ersatz für print() namens hs
Author-email: Florian <deine-email@example.com>
License: MIT
License-File: LICENSE
Dynamic: license-file
